mux/mux.v
// MUX

module mux(OUT, A, B, SEL);
    output OUT;
    input A,B,SEL;
    not I5 (sel_n, SEL) ;
    and I6 (sel_a, A, SEL);
    and I7 (sel_b, sel_n, B);
    or I4 (OUT, sel_a, sel_b);
endmodule

mux/mux_tb.v
module test;

  /* Make a reset that pulses once. */
  reg a = 0, b = 0, sel = 0 ;
    initial begin
        $dumpfile("test.vcd");
        $dumpvars(0,test);
        # 1 a = 0; b = 0; sel = 1;
        # 1 a = 0; b = 1; sel = 0;
        # 1 a = 0; b = 1; sel = 1;
        # 1 a = 1; b = 0; sel = 0;
        # 1 a = 1; b = 0; sel = 1;
        # 1 a = 1; b = 1; sel = 0;
        # 1 a = 1; b = 1; sel = 1;
        # 1 $finish;
    end

  wire out, out2;
  mux m1 (out, a, b, sel);
  mux m2 (out2, out, out, sel);

  initial
     $monitor("At time %t, out = %h (%0d)",
              $time, out, out);
endmodule // test

mux/test.vcd
$date
	Thu Sep 25 16:43:28 2014
$end
$version
	Icarus Verilog
$end
$timescale
	1s
$end
$scope module test $end
$var wire 1 ! out $end
$var wire 1 " out2 $end
$var reg 1 # a $end
$var reg 1 $ b $end
$var reg 1 % sel $end
$scope module m1 $end
$var wire 1 & A $end
$var wire 1 ' B $end
$var wire 1 ! OUT $end
$var wire 1 ( SEL $end
$var wire 1 ) sel_a $end
$var wire 1 * sel_b $end
$var wire 1 + sel_n $end
$upscope $end
$scope module m2 $end
$var wire 1 ! A $end
$var wire 1 ! B $end
$var wire 1 " OUT $end
$var wire 1 ( SEL $end
$var wire 1 , sel_a $end
$var wire 1 - sel_b $end
$var wire 1 . sel_n $end
$upscope $end
$upscope $end
$enddefinitions $end
#0
$dumpvars
1.
0-
0,
1+
0*
0)
0(
0'
0&
0%
0$
0#
0"
0!
$end
#1
0+
0.
1%
1(
#2
1+
1.
0%
0(
1$
1'
#3
1"
1,
1!
0+
1)
0.
1%
1(
#4
1-
1*
1"
1!
1+
1.
0,
0)
0%
0(
0$
0'
1#
1&
#5
0"
0!
0*
0-
0+
0.
0,
1%
1(
#6
1"
1-
1!
1*
1+
1.
0%
0(
1$
1'
#7
0*
0-
0+
1)
0.
1,
1%
1(
